{
  "Routes": [
    {
      "DownstreamPathTemplate": "/api/auth/{everything}",
      "UpstreamPathTemplate": "/identity/{everything}",
      "UpstreamHttpMethod": [ "GET", "POST", "PUT", "DELETE" ],
      "DownstreamScheme": "http",
      "DownstreamHostAndPorts": [
        {
          "Host": "localhost",
          "Port": 7001
        }
      ],
      "AuthenticationOptions": {
        "AuthenticationProviderKey": "GatewayAuth"
      }
    },
    {
      "DownstreamPathTemplate": "/api/wallet/{everything}",
      "UpstreamPathTemplate": "/wallet/{everything}",
      "UpstreamHttpMethod": [ "GET", "POST", "PUT", "DELETE" ],
      "DownstreamScheme": "http",
      "DownstreamHostAndPorts": [
        {
          "Host": "localhost",
          "Port": 7002
        }
      ],
      "AuthenticationOptions": {
        "AuthenticationProviderKey": "GatewayAuth"
      }
    },
    {
      "DownstreamPathTemplate": "/api/payment/{everything}",
      "UpstreamPathTemplate": "/payment/{everything}",
      "UpstreamHttpMethod": [ "GET", "POST", "PUT", "DELETE" ],
      "DownstreamScheme": "http",
      "DownstreamHostAndPorts": [
        {
          "Host": "localhost",
          "Port": 7003
        }
      ],
      "AuthenticationOptions": {
        "AuthenticationProviderKey": "GatewayAuth"
      }
    }
  ],
  "GlobalConfiguration": {
    "BaseUrl": "http://localhost:7000"
  }
}
